ugbio_methylation/__init__.py
ugbio_methylation/concat_methyldackel_csvs.py
ugbio_methylation/generate_methylation_report.py
ugbio_methylation/globals.py
ugbio_methylation/methyldackel_utils.py
ugbio_methylation/process_mbias.py
ugbio_methylation/process_merge_context.py
ugbio_methylation/process_merge_context_no_cp_g.py
ugbio_methylation/process_per_read.py
ugbio_methylation/qc_report_generator.py
ugbio_methylation/reports/methyldackel_qc_report.ipynb
ugbio_methylation-1.20.0.dist-info/METADATA
ugbio_methylation-1.20.0.dist-info/WHEEL
ugbio_methylation-1.20.0.dist-info/entry_points.txt
ugbio_methylation-1.20.0.dist-info/top_level.txt
ugbio_methylation-1.20.0.dist-info/RECORD
