Metadata-Version: 2.4
Name: ugbio_methylation
Version: 1.20.0
Summary: Ultima Genomics methylation bioinfo utils
Author-email: Gat Krieger <gat.krieger@ultimagen.com>, Avigail Moldovan <avigail.moldovan@ultimagen.com>
Requires-Python: >=3.11
Requires-Dist: ugbio_core[reports]
